setup.py
PthMsn_Server_v1.1.egg-info/PKG-INFO
PthMsn_Server_v1.1.egg-info/SOURCES.txt
PthMsn_Server_v1.1.egg-info/dependency_links.txt
PthMsn_Server_v1.1.egg-info/requires.txt
PthMsn_Server_v1.1.egg-info/top_level.txt
src/__init__.py
src/server_start.py
src/common/__init__.py
src/common/decorators.py
src/common/errors.py
src/common/metaclasses.py
src/common/utils.py
src/common/variables.py
src/log/__init__.py
src/log/server_log_config.py
src/server/__init__.py
src/server/del_user.py
src/server/descriptors.py
src/server/reg_user.py
src/server/server_gui.py
src/server/server_storage.py