Metadata-Version: 2.1
Name: PthMsn-Server-v1.1
Version: 1.0
Summary: Python Messenger Server. Version 1.
Home-page: UNKNOWN
Author: NukeDancer
Author-email: nukedancer@yandex.ru
License: UNKNOWN
Platform: UNKNOWN
